Metadata-Version: 2.4
Name: adafruit-circuitpython-display-emoji-text
Version: 1.0.2
Summary: Displayio class for displaying text that contains emoji
Author-email: Adafruit Industries <circuitpython@adafruit.com>
License: MIT
Project-URL: Homepage, https://github.com/adafruit/Adafruit_CircuitPython_Display_Emoji_Text
Keywords: adafruit,blinka,circuitpython,micropython,display_emoji_text,displayio,text,emoji,label,display-text,adafruit_display_text,display
Classifier: Intended Audience :: Developers
Classifier: Topic :: Software Development :: Libraries
Classifier: Topic :: Software Development :: Embedded Systems
Classifier: Topic :: System :: Hardware
Classifier: License :: OSI Approved :: MIT License
Classifier: Programming Language :: Python :: 3
License-File: LICENSE
Requires-Dist: Adafruit-Blinka
Requires-Dist: adafruit-circuitpython-displayio-layout
Provides-Extra: optional
Dynamic: license-file
